ifedit.py
ifedit-0.1.dist-info/LICENSE
ifedit-0.1.dist-info/METADATA
ifedit-0.1.dist-info/WHEEL
ifedit-0.1.dist-info/entry_points.txt
ifedit-0.1.dist-info/RECORD
