Metadata-Version: 2.1
Name: ifedit
Version: 0.1
Summary: A utility to manage contents of ifupdown configuration files.
Home-page: https://github.com/azryve/ifedit
License: MIT
Keywords: ifedit,ifupdown,network,configuration
Author: Fedor Zhukov
Author-email: azryve@gmain.com
Requires-Python: >=3.7
Classifier: License :: OSI Approved :: MIT License
Classifier: Programming Language :: Python :: 3
Classifier: Programming Language :: Python :: 3.7
Classifier: Programming Language :: Python :: 3.8
Classifier: Programming Language :: Python :: 3.9
Classifier: Programming Language :: Python :: 3.10
Classifier: Programming Language :: Python :: 3.11
Classifier: Programming Language :: Python :: 3.12
Project-URL: Repository, https://github.com/azryve/ifedit
